smartpush/__init__.py
smartpush/get_jira_info.py
smartpush/test.py
smartpush/account/__init__.py
smartpush/account/operate_account.py
smartpush/base/__init__.py
smartpush/base/faker_data.py
smartpush/base/request_base.py
smartpush/base/url_enum.py
smartpush/contacts/__init__.py
smartpush/contacts/contacts.py
smartpush/crowd/__init__.py
smartpush/crowd/crowd.py
smartpush/email/__init__.py
smartpush/email/activity.py
smartpush/email/schema.py
smartpush/email/universal_content.py
smartpush/export/__init__.py
smartpush/export/basic/ExcelExportChecker.py
smartpush/export/basic/GetOssUrl.py
smartpush/export/basic/ReadExcel.py
smartpush/export/basic/__init__.py
smartpush/flow/MockFlow.py
smartpush/flow/__init__.py
smartpush/flow/global_flow.py
smartpush/flow/history_flow.py
smartpush/form/__init__.py
smartpush/form/form_after.py
smartpush/form/form_assert.py
smartpush/form/form_before.py
smartpush/form/form_client_operation.py
smartpush/openapi/__init__.py
smartpush/openapi/openapi.py
smartpush/utils/DataTypeUtils.py
smartpush/utils/EmailUtlis.py
smartpush/utils/ListDictUtils.py
smartpush/utils/StringUtils.py
smartpush/utils/__init__.py
smartpush/utils/date_utils.py
smartpush/utils/form_utils.py
smartpush-2.1.2.dist-info/METADATA
smartpush-2.1.2.dist-info/WHEEL
smartpush-2.1.2.dist-info/top_level.txt
smartpush-2.1.2.dist-info/RECORD
