Metadata-Version: 2.1
Name: smartpush
Version: 2.1.2
Summary: 用于smartpush自动化测试工具包
Author: lulu、felix、long
